LICENSE
MANIFEST.in
README
setup.py
ghia/__init__.py
ghia/__main__.py
ghia/assigner.py
ghia/cli.py
ghia/configreader.py
ghia/issue.py
ghia/rule.py
ghia/web.py
ghia/templates/index.html
ghia_nymsapet.egg-info/PKG-INFO
ghia_nymsapet.egg-info/SOURCES.txt
ghia_nymsapet.egg-info/dependency_links.txt
ghia_nymsapet.egg-info/entry_points.txt
ghia_nymsapet.egg-info/not-zip-safe
ghia_nymsapet.egg-info/requires.txt
ghia_nymsapet.egg-info/top_level.txt