Metadata-Version: 1.1
Name: ghia-nymsapet
Version: 0.3.0
Summary: GitHub issue assigner
Home-page: https://github.com/mi-pyt-ghia/petrnymsa
Author: Petr Nymsa
Author-email: nymsapet@fit.cvut.cz
License: MIT
Keywords: github,issue,assign,automatic,label assign,rule based
Platform: UNKNOWN
Classifier: Intended Audience :: Developers
Classifier: License :: OSI Approved :: MIT License
Classifier: Operating System :: POSIX :: Linux
Classifier: Programming Language :: Python
Classifier: Programming Language :: Python :: 3
Classifier: Programming Language :: Python :: 3.6
Classifier: Programming Language :: Python :: 3.7
Classifier: Framework :: Flask
Classifier: Environment :: Console
Classifier: Environment :: Web Environment
Classifier: Topic :: Software Development :: Libraries
